Medimgpy/AverageFilter_demo.py
Medimgpy/EdgeDetect_demo.py
Medimgpy/Example_Im_read&show.py
Medimgpy/GaussianFilter_demo.py
Medimgpy/GaussianFilter_example.py
Medimgpy/Gaussian_example.py
Medimgpy/Homework3_Yhl.py
Medimgpy/ImInformationGet_example.py
Medimgpy/LibFunccall_Mat&Num&PIL.py
Medimgpy/LibFunccall_Num&scipy&Mat.py
Medimgpy/LibFunccall_PIL&xlwt&Mat.py
Medimgpy/ReadMhd_Write2Nrrd.py
Medimgpy/ReadMhd_WriteNifty.py
Medimgpy/ReadMhd_WriteNifty_example.py
Medimgpy/ReadMhd_WriteNrrd_Func.py
Medimgpy/ReadMhd_WriteOther.py
Medimgpy/ReadMhd_Write_2_nrry.py
Medimgpy/SimpleGaussianSmooth_example.py
Medimgpy/TempFilter_Gaussian_example.py
Medimgpy/TempFilter_Implementation_example.py
Medimgpy/Watershed_example.py
Medimgpy/Yanghelin.py
Medimgpy/__init__.py
Medimgpy/__version__.py
Medimgpy/huilib2.py
Medimgpy/huilib_part1.11.16.py
Medimgpy/itk2DImageRegistration.py
Medimgpy/itk3DImageRegistration.py
Medimgpy/itkEdgePreservedSmoothing.py
Medimgpy/itkImageEdgeFiltering.py
Medimgpy/itkImageEnhancement.py
Medimgpy/itkImageLevelSetSegmentation.py
Medimgpy/itkImageOpenClose.py
Medimgpy/itkImageSmoothing.py
Medimgpy/itkRegionGrow.py
Medimgpy/itkVectorFuzzyConnectednessImageFilter.py
Medimgpy/meshSubdivision.py
Medimgpy/panhang3.py
Medimgpy/py_sitk.py
Medimgpy/vtk_SurfaceShow.py
Medimgpy/yhl.py
Medimgpy/yhl_171214.py
Medimgpy/yhl_171221.py
Medimgpy/yhl_hw4(2).py
Medimgpy/yhl_hw4.py
Medimgpy/zx_homework_1228.py
Medimgpy-0.0.9.dist-info/DESCRIPTION.rst
Medimgpy-0.0.9.dist-info/METADATA
Medimgpy-0.0.9.dist-info/RECORD
Medimgpy-0.0.9.dist-info/WHEEL
Medimgpy-0.0.9.dist-info/metadata.json
Medimgpy-0.0.9.dist-info/top_level.txt
