Metadata-Version: 2.0
Name: Medimgpy
Version: 0.0.9
Summary: A friendly Medical Image Processing Library using Python.
Home-page: https://github.com/DlutMedimgGroup/MedImg_Py_Library
Author: KissAndRun
Author-email: taohaihan@outlook.com
License: MIT
Platform: UNKNOWN
Classifier: License :: OSI Approved :: MIT License
Classifier: Programming Language :: Python
Classifier: Programming Language :: Python :: 3
Classifier: Programming Language :: Python :: 3.6
Classifier: Programming Language :: Python :: Implementation :: CPython
Classifier: Programming Language :: Python :: Implementation :: PyPy
Requires-Python: >=3.6.0
Requires-Dist: Pillow
Requires-Dist: SimpleITK
